wslpath/__init__.py
wslpath/_wslpath.py
wslpath_python-0.0.3.dist-info/LICENSE
wslpath_python-0.0.3.dist-info/METADATA
wslpath_python-0.0.3.dist-info/WHEEL
wslpath_python-0.0.3.dist-info/top_level.txt
wslpath_python-0.0.3.dist-info/RECORD
