Metadata-Version: 2.1
Name: wslpath-python
Version: 0.0.3
Summary: Python package for calling wslpath command in WSL environment
Home-page: https://github.com/LoGosX/wslpath-python
Author: Maciej Falbogowski
Author-email: maciej.falbogowski@gmail.com
License: UNKNOWN
Project-URL: Bug Tracker, https://github.com/LoGosX/wslpath-python/issues
Platform: UNKNOWN
Classifier: Programming Language :: Python :: 3
Classifier: License :: OSI Approved :: MIT License
Classifier: Operating System :: OS Independent
Requires-Python: >=3.5
License-File: LICENSE
